apis/__init__.py
apis/config.py
apis/crickbuzz.py
apis/device.py
apis/fbdl.py
apis/getbin.py
apis/imei.py
apis/instadl.py
apis/neko.py
apis/simitalk.py
apis/simiteach.py
apis/trace.py
apis/twitterdl.py
apis/ytdl.py
anbuapis-1.0.0.dist-info/LICENSE
anbuapis-1.0.0.dist-info/METADATA
anbuapis-1.0.0.dist-info/WHEEL
anbuapis-1.0.0.dist-info/top_level.txt
anbuapis-1.0.0.dist-info/RECORD
