Metadata-Version: 2.1
Name: anbuapis
Version: 1.0.0
Summary: A Python module for interacting with the api.anbuinfosec.xyz
Home-page: https://github.com/anbuinfosec/anbuapis
Author: Mohammad Alamin
Author-email: anbuinfosec@gmail.com
Classifier: Programming Language :: Python :: 3
Classifier: Programming Language :: Python :: 3.6
Classifier: Programming Language :: Python :: 3.7
Classifier: Programming Language :: Python :: 3.8
Classifier: License :: OSI Approved :: MIT License
Classifier: Operating System :: OS Independent
Requires-Python: >=3.6
License-File: LICENSE
Requires-Dist: requests
